datacatalog_tag_template_processor/__init__.py
datacatalog_tag_template_processor/constant.py
datacatalog_tag_template_processor/datacatalog_entity_factory.py
datacatalog_tag_template_processor/datacatalog_facade.py
datacatalog_tag_template_processor/datacatalog_tag_template_processor_cli.py
datacatalog_tag_template_processor/tag_template_datasource_processor.py
datacatalog_tag_template_processor-0.2.0.dist-info/AUTHORS.rst
datacatalog_tag_template_processor-0.2.0.dist-info/LICENSE
datacatalog_tag_template_processor-0.2.0.dist-info/METADATA
datacatalog_tag_template_processor-0.2.0.dist-info/WHEEL
datacatalog_tag_template_processor-0.2.0.dist-info/entry_points.txt
datacatalog_tag_template_processor-0.2.0.dist-info/top_level.txt
datacatalog_tag_template_processor-0.2.0.dist-info/RECORD
